<?xml version="1.0" encoding="UTF-8"?>
<!--
  -->
<CCC_Monitor xmlns="urn:schemas-cosylab-com:CCC_Monitor:1.0"
             xmlns:baci="urn:schemas-cosylab-com:BACI:1.0"
             xmlns:cdb="urn:schemas-cosylab-com:CDB:1.0"
             xmlns:xsi="http://www.w3.org/2001/XMLSchema-instance">

	<!-- Correlator Cards monitor points -->
	<voltage_corrCard_1_8v  id="1" description="corr card 1.8v power supply voltage" units="V"/>
	<voltage_corrCard_3_3v  id="2" description="corr card 3.3v power supply voltage" units="V"/>
	<voltage_corrCard_5v    id="3" description="corr card 5v power supply voltage" units="V"/>
	<voltage_corrCard_48v   id="4" description="corr card 48v power supply voltage" units="V"/>
	<current0_corrCard_1_8v id="5" description="corr card 1.8v power supply current0" units="A"/>
	<current1_corrCard_1_8v id="6" description="corr card 1.8v power supply current1" units="A"/>
	<current2_corrCard_1_8v id="7" description="corr card 1.8v power supply current2" units="A"/>
	<temp_corrCard          id="8" description="corr card temperature" units="C"/>

	<!-- 9U bin power supplies -->
	<voltage_9U_1_5v  id="9"  description="9U bin 1.5v power supply voltage" units="V"/>
	<voltage_9U_1_8v  id="10" description="9U bin 1.8v power supply voltage" units="V"/>
	<voltage_9U_3_3v  id="11" description="9U bin 3.3v power supply voltage" units="V"/>
	<voltage_9U_5v    id="12" description="9U bin 5v power supply voltage" units="V"/>
	<voltage_9U_48v   id="13" description="9U bin 48v power supply voltage" units="V"/>
	<current_9U_1_5v  id="14" description="9U bin 1.5v power supply current" units="A"/>
	<current0_9U_1_8v id="15" description="9U bin 1.8v power supply current0" units="A"/>
	<current1_9U_1_8v id="16" description="9U bin 1.8v power supply current1" units="A"/>
	<current2_9U_1_8v id="17" description="9U bin 1.8v power supply current2" units="A"/>
	<current0_9U_3_3v id="18" description="9U bin 3.3v power supply current0" units="A"/>
	<current1_9U_3_3v id="19" description="9U bin 3.3v power supply current1" units="A"/>
	<current_9U_5v    id="20" description="9U bin 5v power supply current" units="A"/>
	<temp_9U          id="21" description="9U bin temperature" units="C"/>

	<!-- 6U bin power supplies -->
	<voltage_6U_1_5v  id="22" description="6U bin 1.5v power supply voltage" units="V"/>
	<voltage_6U_1_8v  id="23" description="6U bin 1.8v power supply voltage" units="V"/>
	<voltage_6U_3_3v  id="24" description="6U bin 3.3v power supply voltage" units="V"/>
	<voltage_6U_5v    id="25" description="6U bin 5v power supply voltage" units="V"/>
	<current_6U_1_5v  id="26" description="6U bin 1.5v power supply current" units="A"/>
	<current0_6U_1_8v id="27" description="6U bin 1.8v power supply current0" units="A"/>
	<current1_6U_1_8v id="28" description="6U bin 1.8v power supply current1" units="A"/>
	<current2_6U_1_8v id="29" description="6U bin 1.8v power supply current2" units="A"/>
	<current0_6U_3_3v id="30" description="6U bin 3.3v power supply current0" units="A"/>
	<current1_6U_3_3v id="31" description="6U bin 3.3v power supply current1" units="A"/>
	<current_6U_5v    id="32" description="6U bin 5v power supply current" units="A"/>
	<temp_6U          id="33" description="6U bin temperature" units="C"/>

	<!-- Power Control Card Bin monitor points -->
	<ground_PCC           id="34" description="PCC ground" units="V"/>
	<voltage_PCC_5v       id="35" description="PCC 5v power supply voltage" units="V"/>
	<voltage_PCC_12v      id="36" description="PCC +-12v power supply voltage (+)" units="V"/>
	<voltage_PCC_minus12v id="37" description="PCC +-12v power supply voltage (-)" units="V"/>
	<current0_PCC         id="38" description="PCC current0" units="A"/>
	<current1_PCC         id="39" description="PCC current1" units="A"/>
	<current2_PCC         id="40" description="PCC current2" units="A"/>
	<temp_PCC             id="41" description="PCC temperature" units="C"/>

	<!-- CCC-related monitor points -->
	<voltage_CCC_5v id="42" description="CCC 5v power supply voltage" units="V"/>
	<temp_CCC       id="43" description="CCC temperature" units="C"/>
	<fanSpeed_CCC   id="44" description="CCC fan speed" units="rpm"/>

	<!-- absolute CAN error counts -->
	<LTA_CAN_ErrorCount id="45" description="LTA CAN bus errors count" units=""/>
	<SCC_CAN_ErrorCount id="46" description="SCC CAN bus errors count" units=""/>
	<QCC_CAN_ErrorCount id="47" description="QCC CAN bus errors count" units=""/>

	<!-- Missed any timing events -->
	<missedTECount id="48" description="Missed Time Events count" units=""/>

</CCC_Monitor>
